Metadata-Version: 1.0
Name: cloudprint
Version: 0.2
Summary: Google cloud print proxy for linux/OSX
Home-page: https://github.com/armooo/cloudprint
Author: Jason Michalski
Author-email: armooo@armooo.net
License: UNKNOWN
Platform: UNKNOWN
Classifier: Development Status :: 4 - Beta
Classifier: Environment :: Console
Classifier: Intended Audience :: End Users/Desktop
Classifier: Operating System :: MacOS :: MacOS X
Classifier: Operating System :: POSIX
Classifier: Topic :: Printing
Classifier: License :: OSI Approved :: GNU General Public License (GPL)
